README.md
setup.py
tec.ic.ia.pc1.g6.egg-info/PKG-INFO
tec.ic.ia.pc1.g6.egg-info/SOURCES.txt
tec.ic.ia.pc1.g6.egg-info/dependency_links.txt
tec.ic.ia.pc1.g6.egg-info/top_level.txt
tec/ic/ia/pc1/g06.py