Metadata-Version: 1.0
Name: tec.ic.ia.pc1.g6
Version: 0.3
Summary: Modulo para la generación de muestras
Home-page: https://github.com/Xbolanos/PC1-IA/
Author: Grupo6-IA-ITCR
Author-email: UNKNOWN
License: UNKNOWN
Platform: UNKNOWN
